CONTRIBUTING.md
LICENSE.md
MANIFEST.in
README.md
setup.py
hmac_authentication/__init__.py
hmac_authentication/hmacauth.py
hmac_authentication.egg-info/PKG-INFO
hmac_authentication.egg-info/SOURCES.txt
hmac_authentication.egg-info/dependency_links.txt
hmac_authentication.egg-info/not-zip-safe
hmac_authentication.egg-info/pbr.json
hmac_authentication.egg-info/requires.txt
hmac_authentication.egg-info/top_level.txt