Metadata-Version: 1.1
Name: hmac-authentication
Version: 1.0.0
Summary: Signs and validates HTTP requests based on a shared-secret HMAC signature
Home-page: https://github.com/18F/hmac_authentication_py
Author: Mike Bland
Author-email: mbland@acm.org
License: As a work of the United States Government, this project is in the
